<list>
  <ProcessDefinition>
    <processDefinitionPK>
      <companyId>1</companyId>
      <processId>cadastroFornecedor</processId>
    </processDefinitionPK>
    <processDescription>Cadastro de Fornecedor</processDescription>
    <instruction></instruction>
    <active>true</active>
    <publicProcess>false</publicProcess>
    <volumeId>Default</volumeId>
    <categoryId>Cadastros</categoryId>
    <managerEngineAllocationId></managerEngineAllocationId>
    <snapshotFrequency>0</snapshotFrequency>
    <baseDay>0</baseDay>
    <baseMonth>0</baseMonth>
    <periodId>Default</periodId>
    <uniqueCardVersion>false</uniqueCardVersion>
    <keyWord></keyWord>
    <complementsLevel>1</complementsLevel>
    <notifyRequisitionerComplements>true</notifyRequisitionerComplements>
    <notifyManagerComplements>false</notifyManagerComplements>
    <deadlineTime>0</deadlineTime>
    <warningDeadlineTime>0</warningDeadlineTime>
    <notifyAuthorityComplements>true</notifyAuthorityComplements>
  </ProcessDefinition>
  <ProcessDefinitionVersion>
    <processDefinitionVersionPK>
      <companyId>1</companyId>
      <processId>Cadastro de Fornecedor</processId>
      <version>3</version>
    </processDefinitionVersionPK>
    <versionDescription></versionDescription>
    <formId>50</formId>
    <editionMode>true</editionMode>
    <updateAttachmentsVersion>false</updateAttachmentsVersion>
    <controlsAttachmentsSecurity>false</controlsAttachmentsSecurity>
    <active>true</active>
    <blockedVersion>false</blockedVersion>
    <counterSign>false</counterSign>
    <openInstances>0</openInstances>
    <bpmnVersion>2</bpmnVersion>
    <processStates/>
    <favorito>false</favorito>
    <inheritFormSecurity>false</inheritFormSecurity>
    <mobileReady>false</mobileReady>
  </ProcessDefinitionVersion>
  <list>
    <ProcessState>
      <processStatePK>
        <companyId>1</companyId>
        <processId>cadastroFornecedor</processId>
        <version>1</version>
        <sequence>4</sequence>
      </processStatePK>
      <stateName>Início</stateName>
      <stateDescription>Início</stateDescription>
      <instruction></instruction>
      <deadlineTime>0</deadlineTime>
      <joint>false</joint>
      <agreementPercentage>0</agreementPercentage>
      <engineAllocationId></engineAllocationId>
      <engineAllocationConfiguration></engineAllocationConfiguration>
      <selectColleague>1</selectColleague>
      <initialState>true</initialState>
      <notifyAuthorityDelay>true</notifyAuthorityDelay>
      <notifyRequisitionerDelay>false</notifyRequisitionerDelay>
      <allowanceAuthorityTime>3600</allowanceAuthorityTime>
      <frequenceAuthorityTime>3600</frequenceAuthorityTime>
      <allowanceRequisitionerTime>0</allowanceRequisitionerTime>
      <frequenceRequisitionerTime>0</frequenceRequisitionerTime>
      <transferAttachments>false</transferAttachments>
      <subProcessId></subProcessId>
      <formFolder>0</formFolder>
      <notifyAuthorityFollowUp>false</notifyAuthorityFollowUp>
      <notifyRequisitionerFollowUp>false</notifyRequisitionerFollowUp>
      <automatic>false</automatic>
      <positionX>150</positionX>
      <positionY>90</positionY>
      <forecastedEffortType>0</forecastedEffortType>
      <forecastedEffort>0</forecastedEffort>
      <notifyManagerFollowUp>false</notifyManagerFollowUp>
      <notifyManagerDelay>false</notifyManagerDelay>
      <allowanceManagerTime>0</allowanceManagerTime>
      <frequenceManagerTime>0</frequenceManagerTime>
      <inhibitTransfer>false</inhibitTransfer>
      <periodId></periodId>
      <stateType>0</stateType>
      <bpmnType>10</bpmnType>
      <signalId>0</signalId>
      <counterSign>false</counterSign>
      <openInstances>0</openInstances>
      <noticeExpirationAuthorityTime>0</noticeExpirationAuthorityTime>
      <noticeExpirationRequisitionerTime>0</noticeExpirationRequisitionerTime>
      <noticeExpirationManagerTime>0</noticeExpirationManagerTime>
      <destinationStates/>
      <digitalSignature>false</digitalSignature>
    </ProcessState>
    <ProcessState>
      <processStatePK>
        <companyId>1</companyId>
        <processId>cadastroFornecedor</processId>
        <version>1</version>
        <sequence>5</sequence>
      </processStatePK>
      <stateName>Finalizar Preenchimento</stateName>
      <stateDescription>Finalizar Preenchimento</stateDescription>
      <instruction></instruction>
      <deadlineTime>0</deadlineTime>
      <deadlineFieldName></deadlineFieldName>
      <joint>false</joint>
      <agreementPercentage>0</agreementPercentage>
      <engineAllocationId>Pool Grupo</engineAllocationId>
      <engineAllocationConfiguration>&lt;AssignmentController&gt;&lt;Group&gt;SETCON&lt;/Group&gt;&lt;/AssignmentController&gt;</engineAllocationConfiguration>
      <selectColleague>1</selectColleague>
      <initialState>false</initialState>
      <notifyAuthorityDelay>true</notifyAuthorityDelay>
      <notifyRequisitionerDelay>false</notifyRequisitionerDelay>
      <allowanceAuthorityTime>3600</allowanceAuthorityTime>
      <frequenceAuthorityTime>3600</frequenceAuthorityTime>
      <allowanceRequisitionerTime>0</allowanceRequisitionerTime>
      <frequenceRequisitionerTime>0</frequenceRequisitionerTime>
      <transferAttachments>false</transferAttachments>
      <subProcessId></subProcessId>
      <formFolder>0</formFolder>
      <notifyAuthorityFollowUp>true</notifyAuthorityFollowUp>
      <notifyRequisitionerFollowUp>false</notifyRequisitionerFollowUp>
      <automatic>false</automatic>
      <positionX>260</positionX>
      <positionY>200</positionY>
      <forecastedEffortType>0</forecastedEffortType>
      <forecastedEffort>0</forecastedEffort>
      <notifyManagerFollowUp>false</notifyManagerFollowUp>
      <notifyManagerDelay>false</notifyManagerDelay>
      <allowanceManagerTime>0</allowanceManagerTime>
      <frequenceManagerTime>0</frequenceManagerTime>
      <inhibitTransfer>false</inhibitTransfer>
      <periodId></periodId>
      <stateType>0</stateType>
      <bpmnType>80</bpmnType>
      <signalId>0</signalId>
      <counterSign>false</counterSign>
      <openInstances>0</openInstances>
      <noticeExpirationAuthorityTime>0</noticeExpirationAuthorityTime>
      <noticeExpirationRequisitionerTime>0</noticeExpirationRequisitionerTime>
      <noticeExpirationManagerTime>0</noticeExpirationManagerTime>
      <destinationStates/>
      <digitalSignature>false</digitalSignature>
      <executionType>0</executionType>
    </ProcessState>
    <ProcessState>
      <processStatePK>
        <companyId>1</companyId>
        <processId>cadastroFornecedor</processId>
        <version>1</version>
        <sequence>11</sequence>
      </processStatePK>
      <stateName>Retornar para Inicio</stateName>
      <stateDescription>Retornar para Inicio</stateDescription>
      <joint>false</joint>
      <initialState>false</initialState>
      <transferAttachments>false</transferAttachments>
      <subProcessId></subProcessId>
      <formFolder>0</formFolder>
      <automatic>true</automatic>
      <positionX>283</positionX>
      <positionY>50</positionY>
      <inhibitTransfer>false</inhibitTransfer>
      <stateType>1</stateType>
      <bpmnType>120</bpmnType>
      <signalId>0</signalId>
      <openInstances>0</openInstances>
      <destinationStates/>
      <digitalSignature>false</digitalSignature>
    </ProcessState>
    <ProcessState>
      <processStatePK>
        <companyId>1</companyId>
        <processId>cadastroFornecedor</processId>
        <version>1</version>
        <sequence>9</sequence>
      </processStatePK>
      <stateName>Fim</stateName>
      <stateDescription>Fim</stateDescription>
      <instruction>Atividade final do processo</instruction>
      <deadlineTime>0</deadlineTime>
      <joint>false</joint>
      <agreementPercentage>0</agreementPercentage>
      <engineAllocationId></engineAllocationId>
      <engineAllocationConfiguration></engineAllocationConfiguration>
      <selectColleague>0</selectColleague>
      <initialState>false</initialState>
      <notifyAuthorityDelay>true</notifyAuthorityDelay>
      <notifyRequisitionerDelay>false</notifyRequisitionerDelay>
      <allowanceAuthorityTime>0</allowanceAuthorityTime>
      <frequenceAuthorityTime>1</frequenceAuthorityTime>
      <allowanceRequisitionerTime>0</allowanceRequisitionerTime>
      <frequenceRequisitionerTime>0</frequenceRequisitionerTime>
      <transferAttachments>false</transferAttachments>
      <subProcessId></subProcessId>
      <formFolder>0</formFolder>
      <notifyAuthorityFollowUp>false</notifyAuthorityFollowUp>
      <notifyRequisitionerFollowUp>false</notifyRequisitionerFollowUp>
      <automatic>false</automatic>
      <positionX>450</positionX>
      <positionY>217</positionY>
      <forecastedEffortType>0</forecastedEffortType>
      <forecastedEffort>0</forecastedEffort>
      <notifyManagerFollowUp>false</notifyManagerFollowUp>
      <notifyManagerDelay>false</notifyManagerDelay>
      <allowanceManagerTime>0</allowanceManagerTime>
      <frequenceManagerTime>0</frequenceManagerTime>
      <inhibitTransfer>false</inhibitTransfer>
      <periodId></periodId>
      <stateType>0</stateType>
      <bpmnType>60</bpmnType>
      <signalId>0</signalId>
      <counterSign>false</counterSign>
      <openInstances>0</openInstances>
      <destinationStates/>
      <digitalSignature>false</digitalSignature>
    </ProcessState>
  </list>
  <list>
    <ConditionProcessState>
      <conditionProcessStatePK>
        <companyId>1</companyId>
        <processId>cadastroFornecedor</processId>
        <expressionOrder>1</expressionOrder>
        <version>3</version>
        <sequence>11</sequence>
      </conditionProcessStatePK>
      <condition>true</condition>
      <destinationSequenceId>4</destinationSequenceId>
      <engineAllocationConfiguration>&lt;AssignmentController&gt;&lt;BaseActivity&gt;4&lt;/BaseActivity&gt;&lt;Returns&gt;Last&lt;/Returns&gt;&lt;/AssignmentController&gt;</engineAllocationConfiguration>
      <engineAllocationId>Executor Atividade</engineAllocationId>
    </ConditionProcessState>
  </list>
  <list>
    <ProcessLink>
      <processLinkPK>
        <companyId>1</companyId>
        <processId>cadastroFornecedor</processId>
        <version>1</version>
        <linkSequence>6</linkSequence>
      </processLinkPK>
      <actionLabel></actionLabel>
      <returnPermited>false</returnPermited>
      <initialStateSequence>4</initialStateSequence>
      <finalStateSequence>5</finalStateSequence>
      <returnLabel></returnLabel>
      <name></name>
      <automaticLink>false</automaticLink>
      <defaultLink>false</defaultLink>
      <type>0</type>
    </ProcessLink>
    <ProcessLink>
      <processLinkPK>
        <companyId>1</companyId>
        <processId>cadastroFornecedor</processId>
        <version>1</version>
        <linkSequence>10</linkSequence>
      </processLinkPK>
      <actionLabel></actionLabel>
      <returnPermited>false</returnPermited>
      <initialStateSequence>5</initialStateSequence>
      <finalStateSequence>9</finalStateSequence>
      <returnLabel></returnLabel>
      <name></name>
      <automaticLink>false</automaticLink>
      <defaultLink>false</defaultLink>
      <type>0</type>
    </ProcessLink>
    <ProcessLink>
      <processLinkPK>
        <companyId>1</companyId>
        <processId>cadastroFornecedor</processId>
        <version>1</version>
        <linkSequence>12</linkSequence>
      </processLinkPK>
      <actionLabel></actionLabel>
      <returnPermited>false</returnPermited>
      <initialStateSequence>5</initialStateSequence>
      <finalStateSequence>11</finalStateSequence>
      <returnLabel></returnLabel>
      <name></name>
      <automaticLink>false</automaticLink>
      <defaultLink>false</defaultLink>
      <type>0</type>
    </ProcessLink>
    <ProcessLink>
      <processLinkPK>
        <companyId>1</companyId>
        <processId>cadastroFornecedor</processId>
        <version>1</version>
        <linkSequence>13</linkSequence>
      </processLinkPK>
      <actionLabel></actionLabel>
      <returnPermited>false</returnPermited>
      <initialStateSequence>11</initialStateSequence>
      <finalStateSequence>4</finalStateSequence>
      <returnLabel></returnLabel>
      <name></name>
      <automaticLink>false</automaticLink>
      <defaultLink>false</defaultLink>
      <type>0</type>
    </ProcessLink>
  </list>
  <list/>
  <list/>
  <list/>
  <list>
    <SwimLane>
      <color>FFFFFF</color>
      <height>290</height>
      <width>831</width>
      <positionX>10</positionX>
      <positionY>10</positionY>
      <stateName>Pool</stateName>
      <type>1</type>
      <parentSequence>0</parentSequence>
      <swimLanePK>
        <companyId>1</companyId>
        <processId>cadastroFornecedor</processId>
        <version>1</version>
        <sequence>1</sequence>
      </swimLanePK>
    </SwimLane>
    <SwimLane>
      <color>9F9F9F</color>
      <height>145</height>
      <width>801</width>
      <positionX>40</positionX>
      <positionY>10</positionY>
      <stateName>Usuário</stateName>
      <type>2</type>
      <parentSequence>1</parentSequence>
      <swimLanePK>
        <companyId>1</companyId>
        <processId>cadastroFornecedor</processId>
        <version>1</version>
        <sequence>2</sequence>
      </swimLanePK>
    </SwimLane>
    <SwimLane>
      <color>C0C0C0</color>
      <height>145</height>
      <width>801</width>
      <positionX>40</positionX>
      <positionY>155</positionY>
      <stateName>Controladoria</stateName>
      <type>2</type>
      <parentSequence>1</parentSequence>
      <swimLanePK>
        <companyId>1</companyId>
        <processId>cadastroFornecedor</processId>
        <version>1</version>
        <sequence>3</sequence>
      </swimLanePK>
    </SwimLane>
  </list>
  <list/>
  <list/>
  <list>
    <ProcessLinkBend>
      <processLinkBendPK>
        <companyId>1</companyId>
        <processId>cadastroFornecedor</processId>
        <version>3</version>
        <linkSequence>6</linkSequence>
        <bendSequence>1</bendSequence>
      </processLinkBendPK>
      <positionX>167</positionX>
      <positionY>235</positionY>
    </ProcessLinkBend>
  </list>
  <list/>
  <list/>
  <list>
    <ProcessFormField>
      <processFormFieldPK>
        <companyId>1</companyId>
        <processId>cadastroFornecedor</processId>
        <fieldId>A2BAIRRO</fieldId>
      </processFormFieldPK>
      <fieldDescription>Bairro</fieldDescription>
      <slotId>1</slotId>
    </ProcessFormField>
    <ProcessFormField>
      <processFormFieldPK>
        <companyId>1</companyId>
        <processId>cadastroFornecedor</processId>
        <fieldId>A2CEP</fieldId>
      </processFormFieldPK>
      <fieldDescription>CEP</fieldDescription>
      <slotId>2</slotId>
    </ProcessFormField>
    <ProcessFormField>
      <processFormFieldPK>
        <companyId>1</companyId>
        <processId>cadastroFornecedor</processId>
        <fieldId>A2DDD</fieldId>
      </processFormFieldPK>
      <fieldDescription>DDD</fieldDescription>
      <slotId>3</slotId>
    </ProcessFormField>
    <ProcessFormField>
      <processFormFieldPK>
        <companyId>1</companyId>
        <processId>cadastroFornecedor</processId>
        <fieldId>A2END</fieldId>
      </processFormFieldPK>
      <fieldDescription>Endereço</fieldDescription>
      <slotId>4</slotId>
    </ProcessFormField>
    <ProcessFormField>
      <processFormFieldPK>
        <companyId>1</companyId>
        <processId>cadastroFornecedor</processId>
        <fieldId>A2EST</fieldId>
      </processFormFieldPK>
      <fieldDescription>Estado</fieldDescription>
      <slotId>5</slotId>
    </ProcessFormField>
    <ProcessFormField>
      <processFormFieldPK>
        <companyId>1</companyId>
        <processId>cadastroFornecedor</processId>
        <fieldId>A2LOJA</fieldId>
      </processFormFieldPK>
      <fieldDescription>Loja</fieldDescription>
      <slotId>6</slotId>
    </ProcessFormField>
    <ProcessFormField>
      <processFormFieldPK>
        <companyId>1</companyId>
        <processId>cadastroFornecedor</processId>
        <fieldId>A2MUN</fieldId>
      </processFormFieldPK>
      <fieldDescription>Municipio</fieldDescription>
      <slotId>7</slotId>
    </ProcessFormField>
    <ProcessFormField>
      <processFormFieldPK>
        <companyId>1</companyId>
        <processId>cadastroFornecedor</processId>
        <fieldId>A2NOME</fieldId>
      </processFormFieldPK>
      <fieldDescription>Razão Social</fieldDescription>
      <slotId>8</slotId>
    </ProcessFormField>
    <ProcessFormField>
      <processFormFieldPK>
        <companyId>1</companyId>
        <processId>cadastroFornecedor</processId>
        <fieldId>A2TELEFONE</fieldId>
      </processFormFieldPK>
      <fieldDescription>Telefone</fieldDescription>
      <slotId>9</slotId>
    </ProcessFormField>
    <ProcessFormField>
      <processFormFieldPK>
        <companyId>1</companyId>
        <processId>cadastroFornecedor</processId>
        <fieldId>dataAbertura</fieldId>
      </processFormFieldPK>
      <fieldDescription>Data Abertura</fieldDescription>
      <slotId>10</slotId>
    </ProcessFormField>
    <ProcessFormField>
      <processFormFieldPK>
        <companyId>1</companyId>
        <processId>cadastroFornecedor</processId>
        <fieldId>matriculaSolicitante</fieldId>
      </processFormFieldPK>
      <fieldDescription>matriculaSolicitante</fieldDescription>
      <slotId>11</slotId>
    </ProcessFormField>
    <ProcessFormField>
      <processFormFieldPK>
        <companyId>1</companyId>
        <processId>cadastroFornecedor</processId>
        <fieldId>nomeSolicitante</fieldId>
      </processFormFieldPK>
      <fieldDescription>Solicitante</fieldDescription>
      <slotId>12</slotId>
    </ProcessFormField>
  </list>
  <list/>
  <list/>
  <list/>
</list>